.gitignore
Dockerfile
LICENSE
README.md
setup.py
examples/list_files_by_dataset_id.py
examples/list_files_by_event_number.py
examples/storage_accounting.py
tests/__init__.py
tests/test_client.py
wipac_fc/__init__.py
wipac_fc/client.py
wipac_fc.egg-info/PKG-INFO
wipac_fc.egg-info/SOURCES.txt
wipac_fc.egg-info/dependency_links.txt
wipac_fc.egg-info/entry_points.txt
wipac_fc.egg-info/requires.txt
wipac_fc.egg-info/top_level.txt