Metadata-Version: 1.2
Name: wipac-fc
Version: 0.0.4
Summary: WIPAC File Catalog Python Client
Home-page: https://github.com/WIPACrepo/wipac_fc
Author: WIPAC
Author-email: contact-us@icecube.wisc.edu
License: UNKNOWN
Platform: UNKNOWN
Classifier: Programming Language :: Python :: 2.7
Classifier: Programming Language :: Python :: 3
Classifier: Programming Language :: Python :: 3.3
Classifier: Programming Language :: Python :: 3.4
Classifier: Programming Language :: Python :: 3.5
Requires-Python: >=2.7
